mcp_excel_supabase/__init__.py
mcp_excel_supabase/server.py
mcp_excel_supabase/excel/__init__.py
mcp_excel_supabase/excel/cell_merger.py
mcp_excel_supabase/excel/data_validator.py
mcp_excel_supabase/excel/dimension_adjuster.py
mcp_excel_supabase/excel/file_merger.py
mcp_excel_supabase/excel/format_applier.py
mcp_excel_supabase/excel/format_editor.py
mcp_excel_supabase/excel/format_extractor.py
mcp_excel_supabase/excel/formula_engine.py
mcp_excel_supabase/excel/formula_manager.py
mcp_excel_supabase/excel/generator.py
mcp_excel_supabase/excel/parser.py
mcp_excel_supabase/excel/schemas.py
mcp_excel_supabase/excel/sheet_manager.py
mcp_excel_supabase/excel/stream_processor.py
mcp_excel_supabase/storage/__init__.py
mcp_excel_supabase/storage/client.py
mcp_excel_supabase/storage/downloader.py
mcp_excel_supabase/storage/manager.py
mcp_excel_supabase/storage/uploader.py
mcp_excel_supabase/tools/__init__.py
mcp_excel_supabase/tools/schemas.py
mcp_excel_supabase/utils/__init__.py
mcp_excel_supabase/utils/cache.py
mcp_excel_supabase/utils/concurrency.py
mcp_excel_supabase/utils/error_handler.py
mcp_excel_supabase/utils/errors.py
mcp_excel_supabase/utils/logger.py
mcp_excel_supabase/utils/monitor.py
mcp_excel_supabase/utils/validator.py
mcp_excel_supabase-1.1.0.dist-info/METADATA
mcp_excel_supabase-1.1.0.dist-info/WHEEL
mcp_excel_supabase-1.1.0.dist-info/entry_points.txt
mcp_excel_supabase-1.1.0.dist-info/licenses/LICENSE
mcp_excel_supabase-1.1.0.dist-info/RECORD
