Metadata-Version: 2.4
Name: mcp-excel-supabase
Version: 1.1.0
Summary: MCP server for Excel operations with Supabase Storage integration
Project-URL: Homepage, https://github.com/1126misakp/Excel-MCP-Server-with-Supabase-Storage
Project-URL: Documentation, https://github.com/1126misakp/Excel-MCP-Server-with-Supabase-Storage/blob/main/docs/README.md
Project-URL: Repository, https://github.com/1126misakp/Excel-MCP-Server-with-Supabase-Storage
Project-URL: Issues, https://github.com/1126misakp/Excel-MCP-Server-with-Supabase-Storage/issues
Author-email: 1126misakp <hikaru_lamperouge@163.com>
License: MIT
License-File: LICENSE
Keywords: automation,excel,mcp,openpyxl,supabase
Classifier: Development Status :: 5 - Production/Stable
Classifier: Intended Audience :: Developers
Classifier: License :: OSI Approved :: MIT License
Classifier: Operating System :: OS Independent
Classifier: Programming Language :: Python :: 3.9
Classifier: Programming Language :: Python :: 3.10
Classifier: Programming Language :: Python :: 3.11
Classifier: Programming Language :: Python :: 3.12
Classifier: Topic :: Office/Business
Classifier: Topic :: Software Development :: Libraries :: Python Modules
Classifier: Typing :: Typed
Requires-Python: >=3.9
Requires-Dist: formulas>=1.2.0
Requires-Dist: mcp>=1.0.0
Requires-Dist: openpyxl>=3.1.0
Requires-Dist: psutil>=5.9.0
Requires-Dist: pydantic>=2.0.0
Requires-Dist: python-dotenv>=1.0.0
Requires-Dist: supabase>=2.0.0
Provides-Extra: dev
Requires-Dist: black>=24.0.0; extra == 'dev'
Requires-Dist: mypy>=1.8.0; extra == 'dev'
Requires-Dist: pip-audit>=2.6.0; extra == 'dev'
Requires-Dist: pytest-asyncio>=0.23.0; extra == 'dev'
Requires-Dist: pytest-cov>=4.1.0; extra == 'dev'
Requires-Dist: pytest-mock>=3.12.0; extra == 'dev'
Requires-Dist: pytest>=8.0.0; extra == 'dev'
Requires-Dist: ruff>=0.3.0; extra == 'dev'
Requires-Dist: types-openpyxl; extra == 'dev'
Requires-Dist: types-psutil; extra == 'dev'
